{"memory-data":[
{ "timestamp": "1682087813", "memory-usage": "42Mi" },
{ "timestamp": "1682087814", "memory-usage": "42Mi" },
{ "timestamp": "1682087815", "memory-usage": "42Mi" },
{ "timestamp": "1682087817", "memory-usage": "42Mi" },
{ "timestamp": "1682087818", "memory-usage": "42Mi" },
{ "timestamp": "1682087819", "memory-usage": "42Mi" },
{ "timestamp": "1682087821", "memory-usage": "42Mi" },
{ "timestamp": "1682087822", "memory-usage": "42Mi" },
{ "timestamp": "1682087823", "memory-usage": "42Mi" },
{ "timestamp": "1682087824", "memory-usage": "42Mi" },
{ "timestamp": "1682087826", "memory-usage": "42Mi" },
{ "timestamp": "1682087827", "memory-usage": "42Mi" },
{ "timestamp": "1682087828", "memory-usage": "42Mi" },
{ "timestamp": "1682087830", "memory-usage": "42Mi" },
{ "timestamp": "1682087831", "memory-usage": "42Mi" },
{ "timestamp": "1682087832", "memory-usage": "42Mi" },
{ "timestamp": "1682087833", "memory-usage": "42Mi" },
{ "timestamp": "1682087835", "memory-usage": "42Mi" },
{ "timestamp": "1682087836", "memory-usage": "42Mi" },
{ "timestamp": "1682087837", "memory-usage": "42Mi" },
{ "timestamp": "1682087838", "memory-usage": "42Mi" },
{ "timestamp": "1682087840", "memory-usage": "42Mi" },
{ "timestamp": "1682087841", "memory-usage": "42Mi" },
{ "timestamp": "1682087842", "memory-usage": "42Mi" },
{ "timestamp": "1682087843", "memory-usage": "42Mi" },
{ "timestamp": "1682087845", "memory-usage": "42Mi" },
{ "timestamp": "1682087846", "memory-usage": "42Mi" },
{ "timestamp": "1682087847", "memory-usage": "42Mi" },
{ "timestamp": "1682087848", "memory-usage": "42Mi" },
{ "timestamp": "1682087850", "memory-usage": "42Mi" },
{ "timestamp": "1682087851", "memory-usage": "42Mi" },
{ "timestamp": "1682087852", "memory-usage": "42Mi" },
{ "timestamp": "1682087854", "memory-usage": "42Mi" },
{ "timestamp": "1682087855", "memory-usage": "42Mi" },
{ "timestamp": "1682087856", "memory-usage": "42Mi" },
{ "timestamp": "1682087858", "memory-usage": "42Mi" },
{ "timestamp": "1682087859", "memory-usage": "42Mi" },
{ "timestamp": "1682087861", "memory-usage": "42Mi" },
{ "timestamp": "1682087863", "memory-usage": "42Mi" },
{ "timestamp": "1682087865", "memory-usage": "42Mi" },
{ "timestamp": "1682087867", "memory-usage": "42Mi" },
{ "timestamp": "1682087869", "memory-usage": "42Mi" },
{ "timestamp": "1682087871", "memory-usage": "42Mi" },
{ "timestamp": "1682087873", "memory-usage": "42Mi" },
{ "timestamp": "1682087875", "memory-usage": "42Mi" },
{ "timestamp": "1682087876", "memory-usage": "42Mi" },
{ "timestamp": "1682087878", "memory-usage": "42Mi" },
{ "timestamp": "1682087879", "memory-usage": "42Mi" },
{ "timestamp": "1682087884", "memory-usage": "42Mi" }
]}
